heic2img/__init__.py
heic2img/main.py
heic2img_converter-0.1.1.dist-info/METADATA
heic2img_converter-0.1.1.dist-info/WHEEL
heic2img_converter-0.1.1.dist-info/entry_points.txt
heic2img_converter-0.1.1.dist-info/licenses/LICENSE
heic2img_converter-0.1.1.dist-info/RECORD
