Metadata-Version: 2.4
Name: heic2img-converter
Version: 0.1.1
Summary: Simple CLI tool to convert HEIC files to JPG, PNG, or WebP
Project-URL: Homepage, https://github.com/jackwatters45/heic2img-converter
Project-URL: Issues, https://github.com/jackwatters45/heic2img-converter/issues
License-Expression: MIT
License-File: LICENSE
Requires-Python: >=3.11.10
Requires-Dist: pillow-heif>=0.13.0
Requires-Dist: pillow>=10.0.0
Requires-Dist: tqdm>=4.65.0
